LICENSE
README.md
setup.py
phimtools/__init__.py
phimtools/main.py
phimtools/utils.py
phimtools.egg-info/PKG-INFO
phimtools.egg-info/SOURCES.txt
phimtools.egg-info/dependency_links.txt
phimtools.egg-info/entry_points.txt
phimtools.egg-info/requires.txt
phimtools.egg-info/top_level.txt
phimtools/launch/__init__.py
phimtools/launch/do.py
phimtools/launch/runfunction.py
phimtools/log/__init__.py
phimtools/modules/__init__.py
phimtools/modules/imputation.py
phimtools/modules/phasing.py
phimtools/tools/__init__.py
phimtools/tools/beagle.py
phimtools/tools/check.py
phimtools/tools/eagle.py
phimtools/tools/minimac.py