Metadata-Version: 2.1
Name: phimtools
Version: 1.1.0
Summary: phimtools: A python program for phasing and imputation NGS data.
Home-page: https://github.com/ShujiaHuang/phimtools
Author: Shujia Huang
Author-email: huangshujia9@gmail.com
Maintainer: Shujia Huang
Maintainer-email: huangshujia9@gmail.com
License: BSD (3-clause)
Download-URL: https://github.com/ShujiaHuang/phimtools
Platform: UNKNOWN
Classifier: Intended Audience :: Science/Research
Classifier: Programming Language :: Python :: 3.7
Classifier: Programming Language :: Python :: 3.8
Classifier: Programming Language :: Python :: 3.9
Classifier: License :: OSI Approved :: BSD License
Classifier: Topic :: Scientific/Engineering :: Bio-Informatics
Classifier: Operating System :: POSIX
Classifier: Operating System :: POSIX :: Linux
